{"stat.useItem.minecraft.string":2,"stat.useItem.minecraft.iron_axe":80,"stat.leaveGame":12,"stat.mineBlock.minecraft.cobblestone":12,"stat.useItem.minecraft.log2":1,"stat.craftItem.minecraft.iron_axe":1,"stat.useItem.minecraft.mutton":4,"stat.swimOneCm":45820,"stat.climbOneCm":83,"stat.useItem.minecraft.planks":2,"achievement.buildWorkBench":2,"stat.breakItem.minecraft.iron_pickaxe":2,"stat.useItem.minecraft.dirt":3,"achievement.exploreAllBiomes":{"value":0,"progress":["ForestHills","Roofed Forest","Birch Forest","Forest","River","Plains","Extreme Hills","Swampland","Extreme Hills+ M"]},"stat.craftItem.minecraft.furnace":2,"stat.useItem.minecraft.egg":1,"stat.craftItem.minecraft.iron_boots":1,"stat.useItem.minecraft.iron_ore":1,"stat.craftItem.minecraft.stone_pickaxe":1,"stat.flyOneCm":32736,"achievement.buildPickaxe":1,"achievement.buildBetterPickaxe":1,"stat.mineBlock.minecraft.iron_ore":1,"stat.timeSinceDeath":85772,"stat.useItem.minecraft.iron_pickaxe":503,"stat.craftItem.minecraft.wooden_pickaxe":1,"stat.furnaceInteraction":10,"stat.useItem.minecraft.cooked_porkchop":3,"stat.mineBlock.minecraft.coal_ore":23,"achievement.mineWood":17,"stat.sprintOneCm":39383,"stat.mineBlock.minecraft.stone_slab":10,"stat.useItem.minecraft.stone_stairs":16,"stat.craftItem.minecraft.stick":52,"stat.craftItem.minecraft.wooden_axe":1,"stat.useItem.minecraft.stone_slab":35,"achievement.openInventory":37,"stat.mineBlock.minecraft.crafting_table":1,"achievement.buildFurnace":2,"stat.drop":2,"stat.playOneMinute":85772,"stat.killEntity.Sheep":2,"stat.craftItem.minecraft.iron_pickaxe":2,"stat.killEntity.Zombie":5,"stat.mineBlock.minecraft.tallgrass":15,"stat.diveOneCm":12874,"stat.useItem.minecraft.chicken":1,"stat.useItem.minecraft.porkchop":4,"stat.jump":1403,"stat.fallOneCm":25837,"stat.crouchOneCm":1376,"stat.craftItem.minecraft.torch":16,"stat.craftItem.minecraft.iron_helmet":1,"stat.useItem.minecraft.cooked_chicken":4,"stat.craftingTableInteraction":7,"stat.mineBlock.minecraft.leaves2":1,"stat.mineBlock.minecraft.log2":27,"stat.mineBlock.minecraft.stone_stairs":4,"stat.damageTaken":446,"stat.mineBlock.minecraft.furnace":1,"stat.useItem.minecraft.reeds":3,"stat.useItem.minecraft.wooden_pickaxe":1,"stat.useItem.minecraft.furnace":3,"stat.mineBlock.minecraft.gravel":29,"stat.useItem.minecraft.stone_pickaxe":51,"stat.craftItem.minecraft.iron_leggings":1,"stat.damageDealt":3540,"stat.killEntity.Cow":1,"stat.useItem.minecraft.crafting_table":5,"stat.mineBlock.minecraft.dirt":20,"stat.killEntity.Pig":1,"stat.craftItem.minecraft.stone_slab":30,"stat.walkOneCm":318222,"stat.useItem.minecraft.torch":17,"stat.playerKills":3,"stat.craftItem.minecraft.stone_stairs":12,"stat.useItem.minecraft.cobblestone":67,"stat.craftItem.minecraft.crafting_table":3,"stat.useItem.minecraft.gravel":24,"stat.craftItem.minecraft.iron_chestplate":1,"stat.craftItem.minecraft.planks":96,"stat.killEntity.Chicken":5,"stat.killEntity.Spider":2,"stat.mobKills":17,"stat.craftItem.minecraft.cooked_chicken":4,"stat.mineBlock.minecraft.leaves":10,"stat.useItem.minecraft.wooden_axe":14,"stat.mineBlock.minecraft.stone":446}