{"stat.useItem.minecraft.iron_axe":34,"stat.leaveGame":33,"stat.mineBlock.minecraft.cobblestone":63,"stat.swimOneCm":52299,"stat.climbOneCm":67339,"achievement.buildWorkBench":6,"stat.useItem.minecraft.dirt":133,"achievement.exploreAllBiomes":{"value":0,"progress":["Sunflower Plains","Roofed Forest","Extreme Hills+","Extreme Hills M","Forest","River","Plains","Taiga","Extreme Hills","Swampland","Extreme Hills+ M"]},"stat.useItem.minecraft.water_bucket":19,"stat.craftItem.minecraft.furnace":1,"stat.entityKilledBy.Spider":1,"achievement.diamondsToYou":1,"stat.craftItem.minecraft.stone_axe":1,"achievement.diamonds":20,"stat.craftItem.minecraft.stone_pickaxe":28,"stat.craftItem.minecraft.cooked_beef":2,"stat.killEntity.Enderman":1,"stat.useItem.minecraft.stone_shovel":173,"stat.craftItem.minecraft.stone_sword":1,"stat.flyOneCm":115718,"achievement.buildPickaxe":61,"stat.useItem.minecraft.cooked_beef":2,"achievement.buildBetterPickaxe":55,"stat.mineBlock.minecraft.iron_ore":148,"stat.timeSinceDeath":7964,"stat.useItem.minecraft.iron_pickaxe":97,"stat.craftItem.minecraft.wooden_pickaxe":3,"stat.craftItem.minecraft.stonebrick":272,"stat.furnaceInteraction":80,"stat.mineBlock.minecraft.coal_ore":288,"stat.killEntity.Creeper":2,"stat.craftItem.minecraft.stone_hoe":1,"stat.mineBlock.minecraft.ladder":4,"stat.entityKilledBy.Skeleton":1,"achievement.buildSword":1,"achievement.mineWood":145,"stat.useItem.minecraft.written_book":2,"stat.sprintOneCm":90229,"stat.craftItem.minecraft.stick":316,"achievement.openInventory":273,"stat.craftItem.minecraft.stone":273,"stat.mineBlock.minecraft.diamond_ore":20,"stat.useItem.minecraft.wheat_seeds":96,"stat.mineBlock.minecraft.crafting_table":8,"stat.useItem.minecraft.dye":27,"stat.useItem.minecraft.bucket":32,"achievement.killEnemy":20,"achievement.buildFurnace":1,"stat.deaths":7,"stat.drop":29,"stat.playOneMinute":575747,"stat.useItem.minecraft.ladder":73,"stat.craftItem.minecraft.iron_pickaxe":2,"stat.killEntity.Zombie":7,"stat.craftItem.minecraft.dye":27,"stat.mineBlock.minecraft.tallgrass":50,"stat.diveOneCm":6668,"stat.chestOpened":212,"stat.craftItem.minecraft.ladder":69,"achievement.buildHoe":1,"stat.useItem.minecraft.stone":95,"stat.craftItem.minecraft.cooked_porkchop":9,"stat.jump":1878,"stat.fallOneCm":24970,"stat.useItem.minecraft.stone_axe":119,"stat.craftItem.minecraft.bread":6,"stat.crouchOneCm":207507,"achievement.killCow":1,"stat.craftItem.minecraft.torch":180,"stat.craftItem.minecraft.iron_ingot":148,"stat.craftItem.minecraft.chest":14,"achievement.makeBread":12,"stat.craftItem.minecraft.iron_helmet":1,"stat.useItem.minecraft.cooked_chicken":11,"stat.craftingTableInteraction":37,"stat.boatOneCm":61561,"stat.useItem.minecraft.sapling":17,"stat.mineBlock.minecraft.lapis_ore":13,"stat.damageTaken":2327,"stat.mineBlock.minecraft.furnace":5,"stat.mineBlock.minecraft.torch":21,"stat.useItem.minecraft.wooden_pickaxe":54,"stat.useItem.minecraft.furnace":6,"stat.mineBlock.minecraft.sapling":1,"stat.entityKilledBy.Zombie":1,"stat.mineBlock.minecraft.gravel":25,"stat.useItem.minecraft.stone_pickaxe":3427,"stat.useItem.minecraft.stone_sword":107,"stat.damageDealt":6955,"stat.killEntity.Silverfish":1,"stat.killEntity.Cow":1,"stat.useItem.minecraft.crafting_table":11,"stat.mineBlock.minecraft.dirt":169,"stat.killEntity.Pig":8,"stat.craftItem.minecraft.stone_shovel":2,"stat.mineBlock.minecraft.monster_egg":1,"stat.walkOneCm":1603784,"stat.useItem.minecraft.torch":180,"stat.useItem.minecraft.bread":4,"stat.useItem.minecraft.chest":14,"stat.playerKills":1,"stat.useItem.minecraft.log":8,"stat.useItem.minecraft.cobblestone":317,"stat.craftItem.minecraft.crafting_table":3,"stat.useItem.minecraft.gravel":7,"stat.useItem.minecraft.lava_bucket":2,"stat.breakItem.minecraft.stone_pickaxe":24,"stat.craftItem.minecraft.boat":2,"stat.mineBlock.minecraft.emerald_ore":6,"stat.breakItem.minecraft.stone_shovel":1,"stat.killEntity.Skeleton":7,"stat.craftItem.minecraft.bucket":3,"stat.mineBlock.minecraft.stonebrick":4,"stat.craftItem.minecraft.planks":472,"stat.killEntity.Spider":3,"stat.mobKills":31,"stat.useItem.minecraft.stonebrick":212,"stat.mineBlock.minecraft.log":149,"stat.useItem.minecraft.stone_hoe":37,"stat.useItem.minecraft.boat":1,"achievement.acquireIron":15,"stat.mineBlock.minecraft.leaves":62,"stat.mineBlock.minecraft.redstone_ore":38,"stat.mineBlock.minecraft.stone":2981}